MANIFEST.in
README.md
requirements.txt
setup.py
keras_adaptive_softmax/__init__.py
keras_adaptive_softmax/embedding.py
keras_adaptive_softmax/softmax.py
keras_adaptive_softmax.egg-info/PKG-INFO
keras_adaptive_softmax.egg-info/SOURCES.txt
keras_adaptive_softmax.egg-info/dependency_links.txt
keras_adaptive_softmax.egg-info/requires.txt
keras_adaptive_softmax.egg-info/top_level.txt
tests/__init__.py
tests/test_embeddings.py
tests/test_softmax.py