Metadata-Version: 2.1
Name: keras-adaptive-softmax
Version: 0.9.0
Summary: adaptive-softmax implemented in Keras
Home-page: https://github.com/CyberZHG/keras-adaptive-softmax
Author: CyberZHG
Author-email: CyberZHG@users.noreply.github.com
License: MIT
Platform: UNKNOWN
Classifier: Programming Language :: Python :: 3
Classifier: License :: OSI Approved :: MIT License
Classifier: Operating System :: OS Independent
